README
setup.py
lib/__init__.py
lib/ccm.py
lib/simple_model_ccm.py
pyccm.egg-info/PKG-INFO
pyccm.egg-info/SOURCES.txt
pyccm.egg-info/dependency_links.txt
pyccm.egg-info/not-zip-safe
pyccm.egg-info/requires.txt
pyccm.egg-info/top_level.txt