Metadata-Version: 1.1
Name: pyccm
Version: 0.4
Summary: Implementation of the Convergent Cross Mapping
Home-page: UNKNOWN
Author: F. B. Laliberté
Author-email: frederic.laliberte@utoronto.ca
License: BSD
Keywords: time series
Platform: UNKNOWN
Classifier: Development Status :: 4 - Beta
Classifier: Intended Audience :: Science/Research
Classifier: Natural Language :: English
Classifier: License :: OSI Approved :: BSD License
Classifier: Programming Language :: Python :: 2.7
Classifier: Topic :: Scientific/Engineering :: Mathematics
